{
    "circuitElementList": [
        "Input",
        "Output",
        "NotGate",
        "OrGate",
        "AndGate",
        "NorGate",
        "NandGate",
        "XorGate",
        "XnorGate",
        "SevenSegDisplay",
        "SixteenSegDisplay",
        "HexDisplay",
        "Multiplexer",
        "BitSelector",
        "Splitter",
        "Power",
        "Ground",
        "ConstantVal",
        "ControlledInverter",
        "TriState",
        "Adder",
        "verilogMultiplier",
        "verilogDivider",
        "verilogPower",
        "verilogShiftLeft",
        "TwoComplement",
        "verilogShiftRight",
        "Rom",
        "RAM",
        "verilogRAM",
        "EEPROM",
        "TflipFlop",
        "JKflipFlop",
        "SRflipFlop",
        "DflipFlop",
        "TTY",
        "Keyboard",
        "Clock",
        "DigitalLed",
        "Stepper",
        "VariableLed",
        "RGBLed",
        "SquareRGBLed",
        "RGBLedMatrix",
        "Button",
        "Demultiplexer",
        "Buffer",
        "SubCircuit",
        "Flag",
        "MSB",
        "LSB",
        "PriorityEncoder",
        "Tunnel",
        "ALU",
        "Decoder",
        "Random",
        "Counter",
        "Dlatch",
        "TB_Input",
        "TB_Output",
        "ForceGate"
    ],
    "annotationList": [
        "Text",
        "Rectangle",
        "Arrow",
        "ImageAnnotation"
    ],
    "inputList": [
        "Random",
        "Dlatch",
        "JKflipFlop",
        "TflipFlop",
        "SRflipFlop",
        "DflipFlop",
        "Buffer",
        "Stepper",
        "Ground",
        "Power",
        "ConstantVal",
        "Input",
        "Clock",
        "Button",
        "Counter"
    ],
    "subCircuitInputList": [
        "Random",
        "Dlatch",
        "JKflipFlop",
        "TflipFlop",
        "SRflipFlop",
        "DflipFlop",
        "Buffer",
        "Stepper",
        "Ground",
        "Power",
        "ConstantVal",
        "Clock",
        "Button",
        "Counter"
    ],
    "elementHierarchy": {
        "Input": [
            {"name":"Input", "value":"Input"},
            {"name":"Button", "value":"Button"},
            {"name":"Power", "value":"Power"},
            {"name":"Ground", "value":"Ground"},
            {"name":"ConstantVal", "value":"Constant Value"},
            {"name":"Stepper", "value":"Stepper"},
            {"name":"Random", "value":"Random"},
            {"name":"Counter", "value":"Counter"}
        ],
        "Output": [
            {"name":"Output", "value":"Output"},
            {"name":"RGBLed", "value":"RGB Led"},
            {"name":"DigitalLed", "value":"Digital Led"},
            {"name":"VariableLed", "value":"Variable Led"},
            {"name":"HexDisplay", "value":"Hex Display"},
            {"name":"SevenSegDisplay", "value":"Seven Segment Display"},
            {"name":"SixteenSegDisplay", "value":"Sixteen Segment Display"},
            {"name":"SquareRGBLed", "value":"Square RGB Led"},
            {"name":"RGBLedMatrix", "value":"RGB Led Matrix"}
        ],
        "Gates": [
            {"name":"AndGate", "value":"And Gate"},
            {"name":"OrGate", "value":"Or Gate"},
            {"name":"NotGate", "value":"Not Gate"},
            {"name":"XorGate", "value":"Xor Gate"},
            {"name":"NandGate", "value":"Nand Gate"},
            {"name":"NorGate", "value":"Nor Gate"},
            {"name":"XnorGate", "value":"Xnor Gate"}
        ],
        "Decoders & Plexers": [
            {"name":"Multiplexer", "value":"Multiplexer"},
            {"name":"Demultiplexer", "value":"Demultiplexer"},
            {"name":"BitSelector", "value":"Bit Selector"},
            {"name":"MSB", "value":"MSB(Most Significant Bit)"},
            {"name":"LSB", "value":"LSB(Least Significant Bit)"},
            {"name":"PriorityEncoder", "value":"Priority Encoder"},
            {"name":"Decoder", "value":"Decoder"}
        ],
        "Sequential Elements": [
            {"name":"DflipFlop", "value":"D flip Flop"},
            {"name":"Dlatch", "value":"D latch"},
            {"name":"TflipFlop", "value":"T flip Flop"},
            {"name":"JKflipFlop", "value":"JK flip Flop"},
            {"name":"SRflipFlop", "value":"SR flip Flop"},
            {"name":"TTY", "value":"TTY"},
            {"name":"Keyboard", "value":"Keyboard"},
            {"name":"Clock", "value":"Clock"},
            {"name":"Rom", "value":"ROM"},
            {"name":"RAM", "value":"RAM"},
            {"name":"verilogRAM", "value":"Verilog RAM"},
            {"name":"EEPROM", "value":"EEPROM"}
        ],
        "Annotation": [
            {"name":"Rectangle", "value":"Rectangle"},
            {"name":"Arrow", "value":"Arrow"},
            {"name":"ImageAnnotation", "value":"Image Annotation"},
            {"name":"Text", "value":"Text"}
        ],
        "Misc": [
            {"name":"TwoComplement", "value":"Two Complement"},
            {"name":"Flag", "value":"Flag"},
            {"name":"Splitter", "value":"Splitter"},
            {"name":"Adder", "value":"Adder"},
            {"name":"ALU", "value":"ALU(Arithmetic and Logical Unit)"},
            {"name":"TriState", "value":"TriState Flip Flop"},
            {"name":"Tunnel", "value":"Tunnel"},
            {"name":"verilogMultiplier", "value":"Verilog Multiplier"},
            {"name":"verilogDivider", "value":"Verilog Divider"},
            {"name":"verilogPower", "value":"Verilog Power"},
            {"name":"verilogShiftLeft", "value":"Verilog Shift Left"},
            {"name":"verilogShiftRight", "value":"Verilog Shift Right"},
            {"name":"Buffer", "value":"Buffer"},
            {"name":"ControlledInverter", "value":"Controlled Inverter"},
            {"name":"TB_Input", "value":"TB Input"},
            {"name":"TB_Output", "value":"TB Output"},
            {"name":"ForceGate", "value":"Force Gate"}
        ]
    }
}